{
   "ACDSee Photo Studio Ultimate 2018 V11.2 Build 1309 (64-Bit)": [
      "AD : Jul 12, 2018",
      "View : 1.9 K",
      "Download : 800"
   ],
   "Autodesk AutoCAD Electrical 2018 (32bit + 64bit)": [
      "AD : Jul 12, 2018",
      "View : 1.9 K",
      "Download : 800"
   ],
   "Betternet VPN 4": [
      "AD : Jul 12, 2018",
      "View : 1.9 K",
      "Download : 800"
   ],
   "EPLAN Electric P8": [
      "AD : Jul 12, 2018",
      "View : 1.9 K",
      "Download : 800"
   ],
   "Google Chrome (86-64bit)": [
      "AD : Jul 12, 2018",
      "View : 1.9 K",
      "Download : 800"
   ],
   "ICare Data Recovery Pro 8.1": [
      "AD : Jul 12, 2018",
      "View : 1.9 K",
      "Download : 800"
   ],
   "Internet Explorer (86-64bit)": [
      "AD : Jul 12, 2018",
      "View : 1.9 K",
      "Download : 800"
   ],
   "Maxthon Cloud Browser": [
      "AD : Jul 12, 2018",
      "View : 1.9 K",
      "Download : 800"
   ],
   "Microsoft Office 2003": [
      "AD : Jul 12, 2018",
      "View : 1.9 K",
      "Download : 800"
   ],
   "Microsoft Office 2007": [
      "AD : Jul 12, 2018",
      "View : 1.9 K",
      "Download : 800"
   ],
   "Microsoft Office 2010 Professional": [
      "AD : Jul 12, 2018",
      "View : 1.9 K",
      "Download : 800"
   ],
   "Movavi Video Editor Business 14": [
      "AD : Jul 12, 2018",
      "View : 1.9 K",
      "Download : 800"
   ],
   "Movavi Video Suite 17": [
      "AD : Jul 12, 2018",
      "View : 1.9 K",
      "Download : 800"
   ],
   "Mozilla Firefox (86-64bit)": [
      "AD : Jul 12, 2018",
      "View : 1.9 K",
      "Download : 800"
   ],
   "Net Scan": [
      "AD : Jul 12, 2018",
      "View : 1.9 K",
      "Download : 800"
   ],
   "Opera (86-64bit)": [
      "AD : Jul 12, 2018",
      "View : 1.9 K",
      "Download : 800"
   ],
   "Phase One Capture One 11": [
      "AD : Jul 12, 2018",
      "View : 1.9 K",
      "Download : 800"
   ],
   "RealVNC Enterprise 6.2.1": [
      "AD : Jul 12, 2018",
      "View : 1.9 K",
      "Download : 800"
   ],
   "Safari": [
      "AD : Jul 12, 2018",
      "View : 1.9 K",
      "Download : 800"
   ],
   "UC Browser": [
      "AD : Jul 12, 2018",
      "View : 1.9 K",
      "Download : 800"
   ],
   "VMix 2012": [
      "AD : Jul 12, 2018",
      "View : 1.9 K",
      "Download : 800"
   ],
   "VMware Workstation Player Commercial 12.5": [
      "AD : Jul 12, 2018",
      "View : 1.9 K",
      "Download : 800"
   ],
   "VMware Workstation Player Commercial V14.1": [
      "AD : Jul 12, 2018",
      "View : 1.9 K",
      "Download : 800"
   ],
   "VMware Workstation Pro V12": [
      "AD : Jul 12, 2018",
      "View : 1.9 K",
      "Download : 800"
   ],
   "Windows 7 Professional (86-64bit)": [
      "AD : Jul 12, 2018",
      "View : 1.9 K",
      "Download : 800"
   ],
   "Windows XP SP3 Pro (X86) Black Elegant Edition 2017": [
      "AD : Jul 12, 2018",
      "View : 1.9 K",
      "Download : 800"
   ],
   "Windows XP Service Pack 2 SP2": [
      "AD : Jul 12, 2018",
      "View : 1.9 K",
      "Download : 800"
   ],
   "Wondershare Filmora 8 (64-Bit)": [
      "AD : Jul 12, 2018",
      "View : 1.9 K",
      "Download : 800"
   ],
   "Wondershare Filmora Scrn (64-Bit)": [
      "AD : Jul 12, 2018",
      "View : 1.9 K",
      "Download : 800"
   ],
   "XSplit Broadcaster": [
      "AD : Jul 12, 2018",
      "View : 1.9 K",
      "Download : 800"
   ]
}